howto/INTRODUCTION.md
howto/__init__.py
howto/__main__.py
howto/addons.py
howto/logger_utils.py
howto/utils.py
howto/validators.py
howto_cli-0.0.5.dist-info/LICENSE
howto_cli-0.0.5.dist-info/METADATA
howto_cli-0.0.5.dist-info/WHEEL
howto_cli-0.0.5.dist-info/entry_points.txt
howto_cli-0.0.5.dist-info/top_level.txt
howto_cli-0.0.5.dist-info/RECORD
