Metadata-Version: 2.1
Name: howto-cli
Version: 0.0.5
Summary: Multi-scenarios CLI tool for tutorials, guides or stories.
Home-page: UNKNOWN
Author: flavienbwk
License: MIT
Platform: UNKNOWN
Classifier: License :: OSI Approved :: MIT License
Classifier: Programming Language :: Python :: 3
Classifier: Programming Language :: Python :: 3.6
Classifier: Programming Language :: Python :: 3.7
Classifier: Programming Language :: Python :: 3.8
Classifier: Programming Language :: Python :: 3.9
Requires-Dist: PyInquirer (==1.0.3)
Requires-Dist: rich (==10.1.0)
